quickumls/__init__.py
quickumls/about.py
quickumls/client.py
quickumls/constants.py
quickumls/core.py
quickumls/install.py
quickumls/network.py
quickumls/server.py
quickumls/spacy_component.py
quickumls/toolbox.py
quickumls/umls_match.py
resources/quickumls/QuickUMLS_SAMPLE_lowercase_POSIX_unqlite/README.md
resources/quickumls/QuickUMLS_SAMPLE_lowercase_POSIX_unqlite/database_backend.flag
resources/quickumls/QuickUMLS_SAMPLE_lowercase_POSIX_unqlite/language.flag
resources/quickumls/QuickUMLS_SAMPLE_lowercase_POSIX_unqlite/lowercase.flag
resources/quickumls/QuickUMLS_SAMPLE_lowercase_POSIX_unqlite/normalize-unicode.flag
resources/quickumls/QuickUMLS_SAMPLE_lowercase_POSIX_unqlite/cui-semtypes.db/cui.unqlite
resources/quickumls/QuickUMLS_SAMPLE_lowercase_POSIX_unqlite/cui-semtypes.db/semtypes.unqlite
resources/quickumls/QuickUMLS_SAMPLE_lowercase_POSIX_unqlite/umls-simstring.db/umls-terms.simstring
resources/quickumls/QuickUMLS_SAMPLE_lowercase_POSIX_unqlite/umls-simstring.db/umls-terms.simstring.120.cdb
resources/quickumls/QuickUMLS_SAMPLE_lowercase_POSIX_unqlite/umls-simstring.db/umls-terms.simstring.14.cdb
resources/quickumls/QuickUMLS_SAMPLE_lowercase_POSIX_unqlite/umls-simstring.db/umls-terms.simstring.15.cdb
resources/quickumls/QuickUMLS_SAMPLE_lowercase_POSIX_unqlite/umls-simstring.db/umls-terms.simstring.17.cdb
resources/quickumls/QuickUMLS_SAMPLE_lowercase_POSIX_unqlite/umls-simstring.db/umls-terms.simstring.20.cdb
resources/quickumls/QuickUMLS_SAMPLE_lowercase_POSIX_unqlite/umls-simstring.db/umls-terms.simstring.21.cdb
resources/quickumls/QuickUMLS_SAMPLE_lowercase_POSIX_unqlite/umls-simstring.db/umls-terms.simstring.22.cdb
resources/quickumls/QuickUMLS_SAMPLE_lowercase_POSIX_unqlite/umls-simstring.db/umls-terms.simstring.24.cdb
resources/quickumls/QuickUMLS_SAMPLE_lowercase_POSIX_unqlite/umls-simstring.db/umls-terms.simstring.26.cdb
resources/quickumls/QuickUMLS_SAMPLE_lowercase_POSIX_unqlite/umls-simstring.db/umls-terms.simstring.27.cdb
medspacy_quickumls-3.1.dist-info/LICENSE.txt
medspacy_quickumls-3.1.dist-info/METADATA
medspacy_quickumls-3.1.dist-info/WHEEL
medspacy_quickumls-3.1.dist-info/top_level.txt
medspacy_quickumls-3.1.dist-info/RECORD
