Metadata-Version: 2.1
Name: medspacy_quickumls
Version: 3.1
Summary: QuickUMLS is a tool for fast, unsupervised biomedical concept extraction from medical text
Home-page: https://github.com/Georgetown-IR-Lab/QuickUMLS
Author: Luca Soldaini, modified by Kelly Peterson and Jianlin Shi
Author-email: luca@ir.cs.georgetown.edu,kelly.peterson@hsc.utah.edu,jianlin.shi@hsc.utah.edu
License: MIT
Classifier: Programming Language :: Python :: 3
Classifier: Programming Language :: Python :: 2
Classifier: License :: OSI Approved :: MIT License
Classifier: Operating System :: OS Independent
Classifier: Development Status :: 5 - Production/Stable
Classifier: Topic :: Scientific/Engineering :: Artificial Intelligence
Classifier: Topic :: Scientific/Engineering :: Bio-Informatics
License-File: LICENSE.txt
Requires-Dist: numpy >=1.8.2
Requires-Dist: spacy >=3.1.3
Requires-Dist: unidecode >=0.4.19
Requires-Dist: nltk >=3.3
Requires-Dist: pysimstring
Requires-Dist: medspacy-unqlite >=0.8.1
Requires-Dist: pytest >=6
Requires-Dist: six
